ShynaProcess/Shprocess.py
ShynaProcess/ShynaBotNotification.py
ShynaProcess/ShynaBroadcastMessageDecision.py
ShynaProcess/ShynaGetQuotes.py
ShynaProcess/ShynaGoogleSearch.py
ShynaProcess/ShynaGreetings.py
ShynaProcess/ShynaJokes.py
ShynaProcess/ShynaLookForCameraUrl.py
ShynaProcess/ShynaMailClient.py
ShynaProcess/ShynaMovie.py
ShynaProcess/ShynaNews.py
ShynaProcess/ShynaRegexExtraction.py
ShynaProcess/ShynaSentenceAnalyzer.py
ShynaProcess/ShynaSpeak.py
ShynaProcess/ShynaWeather.py
ShynaProcess/ShynaWikiSearch.py
ShynaProcess/ShynaWordnet.py
ShynaProcess/Shyna_PC_Process.py
ShynaProcess/__init__.py
ShynaProcess-0.39.dist-info/LICENSE
ShynaProcess-0.39.dist-info/METADATA
ShynaProcess-0.39.dist-info/WHEEL
ShynaProcess-0.39.dist-info/top_level.txt
ShynaProcess-0.39.dist-info/RECORD
