Metadata-Version: 2.1
Name: ShynaProcess
Version: 0.39
Summary: Shyna Backend Functionality Package For phase one processing
Author: Shivam Sharma
Author-email: shivamsharma1913@gmail.com
License-File: LICENSE
Requires-Dist: setuptools
Requires-Dist: wheel
Requires-Dist: requests
Requires-Dist: nltk
Requires-Dist: feedparser
Requires-Dist: certifi
Requires-Dist: ShynaTime
Requires-Dist: google-speech
Requires-Dist: ShynaDatabase
Requires-Dist: googlesearch-python
Requires-Dist: wikipedia
Requires-Dist: sox
Requires-Dist: python-telegram-bot
Requires-Dist: IMDbPY
Requires-Dist: wget
